Topsis3431/Topsis.py
Topsis3431/__init__.py
Topsis3431-1.0.0.dist-info/LICENSE.txt
Topsis3431-1.0.0.dist-info/METADATA
Topsis3431-1.0.0.dist-info/WHEEL
Topsis3431-1.0.0.dist-info/top_level.txt
Topsis3431-1.0.0.dist-info/RECORD
