Metadata-Version: 2.1
Name: Topsis3431
Version: 1.0.0
Summary: TOPSIS package for MCDM
Home-page: https://github.com/pypa/sampleproject
Author: Rakshit Rajesh Jain
Author-email: rakshitj.1899@gmail.com
License: UNKNOWN
Platform: UNKNOWN
Classifier: Programming Language :: Python :: 3
Classifier: License :: OSI Approved :: MIT License
Classifier: Operating System :: OS Independent
Requires-Python: >=3.7
